autofiller/__init__.py
autofiller/__main__.py
autofiller-1.0.2.dist-info/METADATA
autofiller-1.0.2.dist-info/WHEEL
autofiller-1.0.2.dist-info/licenses/LICENSE.txt
autofiller-1.0.2.dist-info/RECORD
