Metadata-Version: 2.3
Name: autofiller
Version: 1.0.2
Summary: A small popup to input various random data for you
Project-URL: Documentation, https://github.com/smartycope/autofiller#readme
Project-URL: Issues, https://github.com/smartycope/autofiller/issues
Project-URL: Source, https://github.com/smartycope/autofiller
Author-email: Copeland Carter <smartycope@gmail.com>
License-Expression: MIT
License-File: LICENSE.txt
Classifier: Development Status :: 4 - Beta
Classifier: Programming Language :: Python
Classifier: Programming Language :: Python :: 3.10
Classifier: Programming Language :: Python :: 3.11
Classifier: Programming Language :: Python :: 3.12
Classifier: Programming Language :: Python :: Implementation :: CPython
Classifier: Programming Language :: Python :: Implementation :: PyPy
Requires-Python: >=3.10
Requires-Dist: ezregex
Requires-Dist: pynput
Requires-Dist: pyside6
Requires-Dist: pysidesix-frameless-window
Requires-Dist: random-name
